falocalrepo_database/__init__.py
falocalrepo_database/__version__.py
falocalrepo_database/column.py
falocalrepo_database/database.py
falocalrepo_database/exceptions.py
falocalrepo_database/selector.py
falocalrepo_database/tables.py
falocalrepo_database/types.py
falocalrepo_database/update.py
falocalrepo_database/util.py
falocalrepo_database-5.4.6.dist-info/LICENSE
falocalrepo_database-5.4.6.dist-info/WHEEL
falocalrepo_database-5.4.6.dist-info/METADATA
falocalrepo_database-5.4.6.dist-info/RECORD
