Metadata-Version: 2.1
Name: falocalrepo-database
Version: 5.4.6
Summary: Database functionality for falocalrepo.
Home-page: https://github.com/FurryCoders/falocalrepo-database
License: EUPL-1.2
Author: Matteo Campinoti
Author-email: matteo.campinoti94@gmail.com
Requires-Python: >=3.10,<4.0
Classifier: Development Status :: 5 - Production/Stable
Classifier: Intended Audience :: End Users/Desktop
Classifier: License :: OSI Approved :: European Union Public Licence 1.2 (EUPL 1.2)
Classifier: Operating System :: OS Independent
Classifier: Programming Language :: Python :: 3
Classifier: Programming Language :: Python :: 3.10
Classifier: Programming Language :: Python :: 3.11
Classifier: Programming Language :: Python :: 3.10
Classifier: Topic :: Database
Requires-Dist: chardet (>=5.2.0,<6.0.0)
Requires-Dist: filetype (>=1.2.0,<2.0.0)
Requires-Dist: psutil (>=6.0.0,<7.0.0)
Project-URL: Changelog, https://github.com/FurryCoders/falocalrepo-database/blob/master/CHANGELOG.md
Project-URL: Download, https://pypi.org/project/falocalrepo-database/#files
Project-URL: Repository, https://github.com/FurryCoders/falocalrepo-database
Project-URL: Source, https://github.com/FurryCoders/falocalrepo-database
